avl_axi/__init__.py
avl_axi/_agent.py
avl_axi/_agent_cfg.py
avl_axi/_bandwidth.py
avl_axi/_coverage.py
avl_axi/_driver.py
avl_axi/_emonitor.py
avl_axi/_interface.py
avl_axi/_item.py
avl_axi/_mrdriver.py
avl_axi/_msequence.py
avl_axi/_mwakedriver.py
avl_axi/_mwdriver.py
avl_axi/_rmonitor.py
avl_axi/_signals.py
avl_axi/_smemory.py
avl_axi/_srdriver.py
avl_axi/_swdriver.py
avl_axi/_tools.py
avl_axi/_types.py
avl_axi/_utils.py
avl_axi/_wmonitor.py
avl_axi/rtl/avl_axi.sv
avl_axi-0.4.0.dist-info/METADATA
avl_axi-0.4.0.dist-info/WHEEL
avl_axi-0.4.0.dist-info/entry_points.txt
avl_axi-0.4.0.dist-info/licenses/LICENSE
avl_axi-0.4.0.dist-info/RECORD
