Metadata-Version: 2.4
Name: avl-axi
Version: 0.4.0
Summary: Apheleia Verification Library - AMBA AXI verification component.
License: MIT License
License-File: LICENSE
Author: avl
Author-email: avl@projectapheleia.net
Maintainer: avl
Maintainer-email: avl@projectapheleia.net
Requires-Python: >=3.10
Classifier: Development Status :: 4 - Beta
Classifier: Programming Language :: Python
Provides-Extra: dev
Requires-Dist: avl-core (>=0.4.1)
Requires-Dist: black (>=22.3.0) ; extra == "dev"
Requires-Dist: matplotlib (>=3.10.0)
Requires-Dist: mypy (>=0.910) ; extra == "dev"
Requires-Dist: pytest (>=7.0) ; extra == "dev"
Requires-Dist: ruff (>=0.11.0) ; extra == "dev"
Requires-Dist: sphinx (>=8.1.3) ; extra == "dev"
Requires-Dist: sphinx_rtd_theme (>=3.0.2) ; extra == "dev"
